densecall/__init__.py
densecall/__main__.py
densecall/aligner.py
densecall/classes.py
densecall/data.py
densecall/fast5.py
densecall/io.py
densecall/mod_util.py
densecall/multiprocessing.py
densecall/optimize.py
densecall/pod5.py
densecall/read.py
densecall/reader.py
densecall/schedule.py
densecall/slow5.py
densecall/training.py
densecall/util.py
densecall/cli/__init__.py
densecall/cli/accuracy.py
densecall/cli/basecaller.py
densecall/cli/download.py
densecall/cli/train.py
densecall/conformer/__init__.py
densecall/conformer/basecall.py
densecall/conformer/cgmlp.py
densecall/conformer/conv.py
densecall/conformer/criterion.py
densecall/conformer/flash.py
densecall/conformer/linformer.py
densecall/conformer/modcall.py
densecall/conformer/model copy.py
densecall/conformer/model.py
densecall/conformer/modules.py
densecall/conformer/nn.py
densecall/conformer/optimize.py
densecall/conformer/reversible.py
densecall/conformer/util.py
densecall/conformer/wav2vec2.py
densecall/models/configs/conformer.toml
densecall/models/configs/conformer_fast.toml
densecall-0.0.2.8.5.dist-info/LICENCE.txt
densecall-0.0.2.8.5.dist-info/METADATA
densecall-0.0.2.8.5.dist-info/WHEEL
densecall-0.0.2.8.5.dist-info/entry_points.txt
densecall-0.0.2.8.5.dist-info/top_level.txt
densecall-0.0.2.8.5.dist-info/RECORD
