Metadata-Version: 2.1
Name: densecall
Version: 0.0.2.8.5
Author: linlian
Author-email: 21620151153308@stu.xmu.edu.cn
License-File: LICENCE.txt
Requires-Dist: ont-bonito (==1.0.0)
Requires-Dist: torch (==2.9.1)
Requires-Dist: torchaudio (==2.9.1)
Requires-Dist: torchvision (==0.24.1)
Requires-Dist: ont-koi (==0.6.5)
Requires-Dist: Cython (==0.29.21)
Requires-Dist: setuptools (==67.6.1)
Requires-Dist: numpy (==1.23.5)
Requires-Dist: mappy (==2.24)
Requires-Dist: fitter (==1.7.1)
Requires-Dist: pyslow5 (==1.3.1)
Requires-Dist: blue-crab (==0.4.0)
Requires-Dist: toml (==0.10.2)
Requires-Dist: tqdm (<5,>4)
Requires-Dist: scipy (==1.14.1)
Requires-Dist: pysam (==0.21.0)
Requires-Dist: parasail (==1.3.4)
Requires-Dist: pandas (==1.5.3)
Requires-Dist: requests (~=2.32.2)
Requires-Dist: ont-fast5-api (==4.1.3)
Requires-Dist: fast-ctc-decode (==0.3.5)
Requires-Dist: python-dateutil (==2.8.2)
Requires-Dist: pytorch-ranger (==0.1.1)
Requires-Dist: dtaidistance (==2.3.11)
Requires-Dist: torch-pruning (==1.3.7)
Requires-Dist: ruptures (==1.1.9)
Requires-Dist: tslearn (==0.6.3)
Requires-Dist: matplotlib
Requires-Dist: seaborn
Requires-Dist: biopython (==1.86)
Requires-Dist: igv (==0.9.6)
Requires-Dist: deap (==1.4.1)
Requires-Dist: tabulate (==0.9.0)
Requires-Dist: onnx-simplifier (==0.4.36)
Requires-Dist: onnx2torch (==1.5.14)
Requires-Dist: onnxconverter-common (==1.14.0)
Requires-Dist: onnxmltools (==1.12.0)
Requires-Dist: onnxruntime-gpu (==1.22.0)
Requires-Dist: onnxscript (==0.5.1)
Requires-Dist: memory-efficient-attention-pytorch (==0.1.6)
Requires-Dist: edlib (==1.3.9)
Requires-Dist: ont-remora (==3.3.0)
Requires-Dist: rotary-embedding-torch (==0.8.3)
Requires-Dist: debugpy (==1.8.8)
Requires-Dist: statsmodels
Requires-Dist: transformers
Requires-Dist: uncalled4
Requires-Dist: lhotse
Requires-Dist: nltk (==3.9.1)
Requires-Dist: muon-optimizer (==0.1.0)
Requires-Dist: pytorch-crf (==0.7.2)
Requires-Dist: accelerate
Requires-Dist: flashlight (==0.1.1)
Requires-Dist: flashlight-text (==0.0.7)
Requires-Dist: kenlm (==0.3.0)
Requires-Dist: pyabf
Requires-Dist: hyperopt
Requires-Dist: tensorboard
Requires-Dist: patchworklib (==0.6.5)
